{"cards":[{"id":"TheAxe:Oopsy","name":"Oopsy","color":"Curse","rarity":"Curse","type":"Curse","cost":"","description":"Retain.\nUnplayable.","mod":"The Axe"},{"id":"TheAxe:BattleHunger","name":"Battle Hunger","color":"Axe_color","rarity":"Basic","type":"Skill","cost":"1","description":"Apply 5 (7) theaxe:Bloodlust.","mod":"The Axe"},{"id":"TheAxe:BerserkersCall","name":"Berserker's Call","color":"Axe_color","rarity":"Basic","type":"Skill","cost":"1","description":"Gain 9 (12) Block.\nThe enemy instantly attacks you for 2 damage.","mod":"The Axe"},{"id":"TheAxe:Defend","name":"Defend","color":"Axe_color","rarity":"Basic","type":"Skill","cost":"1","description":"Gain 5 (8) Block.","mod":"The Axe"},{"id":"TheAxe:Strike","name":"Strike","color":"Axe_color","rarity":"Basic","type":"Attack","cost":"1","description":"Deal 6 (9) damage.","mod":"The Axe"},{"id":"TheAxe:AxeRuns","name":"Axe Runs","color":"Axe_color","rarity":"Common","type":"Skill","cost":"1","description":"Gain 6 (8) Block.\nGain 1 (2) theaxe:Spin.","mod":"The Axe"},{"id":"TheAxe:BabysitTheCarry","name":"Babysit The Carry","color":"Axe_color","rarity":"Common","type":"Attack","cost":"1","description":"Gain Block and deal damage equal to  (2 + ) your current hand size.","mod":"The Axe"},{"id":"TheAxe:BlastRig","name":"Blast Rig","color":"Axe_color","rarity":"Common","type":"Skill","cost":"","description":"theaxe:Item.\nWhen Retained, gain 3 (4) theaxe:Vigor.\nOn Exhaust, gain twice as much theaxe:Vigor.","mod":"The Axe"},{"id":"TheAxe:BootsOfSpeed","name":"Boots Of Speed","color":"Axe_color","rarity":"Common","type":"Skill","cost":"1 (0)","description":"Reduce the cost of a random card in your hand to 0 this turn.\nDraw 2 cards.\nExhaust.","mod":"The Axe"},{"id":"TheAxe:ComeToAxe","name":"Come To Axe!","color":"Axe_color","rarity":"Common","type":"Skill","cost":"0","description":"The enemy instantly attacks you for 2 damage.\nApply 1 (2) Vulnerable.","mod":"The Axe"},{"id":"TheAxe:CutAndRun","name":"Cut And Run","color":"Axe_color","rarity":"Common","type":"Attack","cost":"1","description":"Deal 6 (9) damage.\nDraw 1 card.\nNext turn, draw 1 additional card.","mod":"The Axe"},{"id":"TheAxe:DrawCreepAggro","name":"Draw Creep Aggro","color":"Axe_color","rarity":"Common","type":"Attack","cost":"0","description":"Deal 2 Damage.\nGain 1 (2) theaxe:Spin.\nExhaust.","mod":"The Axe"},{"id":"TheAxe:ForceARetreat","name":"Force A Retreat","color":"Axe_color","rarity":"Common","type":"Skill","cost":"1","description":"Apply 3 (4) theaxe:Bloodlust to ALL enemies.\nALL enemies lose 3 (4) Strength this turn.\nExhaust.","mod":"The Axe"},{"id":"TheAxe:HarassingStrike","name":"Harassing Strike","color":"Axe_color","rarity":"Common","type":"Attack","cost":"1","description":"Deal 7 (9) damage.\nApply 3 (4) theaxe:Bloodlust.","mod":"The Axe"},{"id":"TheAxe:HardRead","name":"Hard Read","color":"Axe_color","rarity":"Common","type":"Skill","cost":"2","description":"Gain 10 (14) Block.\nPut a card from your discard pile on top of your draw pile.\nDraw 2 cards.\nExhaust.","mod":"The Axe"},{"id":"TheAxe:Initiate","name":"Initiate","color":"Axe_color","rarity":"Common","type":"Attack","cost":"2","description":"Retain.\nDeal 16 (20) damage.\nYou may Exhaust 1 card in your hand.","mod":"The Axe"},{"id":"TheAxe:Juke","name":"Juke","color":"Axe_color","rarity":"Common","type":"Skill","cost":"0","description":"Gain 3 (5) Block.\nNext turn, gain 2 (3) Block.","mod":"The Axe"},{"id":"TheAxe:LuckySpin","name":"Lucky Spin","color":"Axe_color","rarity":"Common","type":"Attack","cost":"1","description":"If the enemy intends to attack, deal 12 (16) damage.","mod":"The Axe"},{"id":"TheAxe:ObserverWard","name":"Observer Ward","color":"Axe_color","rarity":"Common","type":"Skill","cost":"1","description":"Gain 5 (7) Block.\nApply 3 (5) theaxe:Bloodlust to ALL enemies.","mod":"The Axe"},{"id":"TheAxe:OverExtend","name":"Over-Extend","color":"Axe_color","rarity":"Common","type":"Attack","cost":"1 (0)","description":"Deal damage equal to double your theaxe:Spin.","mod":"The Axe"},{"id":"TheAxe:Radiance","name":"Radiance","color":"Axe_color","rarity":"Common","type":"Skill","cost":"","description":"theaxe:Item.\nWhen Retained, apply 2 theaxe:Bloodlust to ALL enemies.\nOn Exhaust, apply 4 (7) instead.","mod":"The Axe"},{"id":"TheAxe:SentryWard","name":"Sentry Ward","color":"Axe_color","rarity":"Common","type":"Skill","cost":"1","description":"Scry 3 (5).\nDraw 2 cards.","mod":"The Axe"},{"id":"TheAxe:SpinToWin","name":"Spin To Win","color":"Axe_color","rarity":"Common","type":"Attack","cost":"1","description":"Deal 2 (3) damage to ALL enemies 3 times.\nDraw 1 card.","mod":"The Axe"},{"id":"TheAxe:TownPortalScroll","name":"Town Portal Scroll","color":"Axe_color","rarity":"Common","type":"Skill","cost":"0","description":"Next turn, gain [E] and draw 1 (2) additional card (cards).\nEnd your turn. Exhaust.","mod":"The Axe"},{"id":"TheAxe:TradeBlows","name":"Trade Blows","color":"Axe_color","rarity":"Common","type":"Attack","cost":"0","description":"Deal 6 (9) damage to each enemy that intends to attack.","mod":"The Axe"},{"id":"TheAxe:VoidStone","name":"Void Stone","color":"Axe_color","rarity":"Common","type":"Skill","cost":"","description":"theaxe:Item.\nWhen Retained, also Retain up to 1 (2) [E].\nOn Exhaust, gain 1 (2) additional [E] next turn.","mod":"The Axe"},{"id":"TheAxe:WorthIt","name":"Worth It","color":"Axe_color","rarity":"Common","type":"Attack","cost":"1","description":"Deal 9 (11) damage.\nApply 1 (2) Weak.\nGain 1 Weak.","mod":"The Axe"},{"id":"TheAxe:AghanimsShard","name":"Aghanim's Shard","color":"Axe_color","rarity":"Uncommon","type":"Power","cost":"1","description":"When you lose HP, gain 1 (2) theaxe:Spin and apply 1 Weak to ALL enemies.","mod":"The Axe"},{"id":"TheAxe:BlinkDagger","name":"Blink Dagger","color":"Axe_color","rarity":"Uncommon","type":"Skill","cost":"0","description":"Apply 1 (2) Vulnerable.\nApply 1 (2) theaxe:Bloodlust.\nDraw 1 card.\nAdd a Dazed to your hand.","mod":"The Axe"},{"id":"TheAxe:Bloodthorn","name":"Bloodthorn","color":"Axe_color","rarity":"Uncommon","type":"Skill","cost":"1","description":"When the target deals damage, they gain 3 (5) theaxe:Bloodlust instead of losing any.\nExhaust.","mod":"The Axe"},{"id":"TheAxe:Chainmail","name":"Chainmail","color":"Axe_color","rarity":"Uncommon","type":"Skill","cost":"","description":"theaxe:Item.\nWhen Retained, gain 2 (3) Block.\nOn Exhaust, gain that plus an additional 3 (6) Block.","mod":"The Axe"},{"id":"TheAxe:CheckForRune","name":"Check For Rune","color":"Axe_color","rarity":"Uncommon","type":"Skill","cost":"1","description":"Choose one:\n2 (3) Vulnerable, 2 (3) Weak, 2 (3) theaxe:Metallicize, draw 2 (3),\n1 (2) theaxe:Blur, or [E]   (now and ) [E]  ( [E]  ) next turn.\nExhaust.","mod":"The Axe"},{"id":"TheAxe:CrimsonGuard","name":"Crimson Guard","color":"Axe_color","rarity":"Uncommon","type":"Power","cost":"2","description":"Gain Dexterity equal to  (1 + ) half of your current hand size.","mod":"The Axe"},{"id":"TheAxe:CutTheWave","name":"Cut The Wave","color":"Axe_color","rarity":"Uncommon","type":"Skill","cost":"0","description":"~~- Gain 1 Vulnerable. -~~\nAt the start of your next turn, deal 15 damage to ALL enemies.","mod":"The Axe"},{"id":"TheAxe:Decapitate","name":"Decapitate","color":"Axe_color","rarity":"Uncommon","type":"Attack","cost":"1","description":"Deal damage for each card in your hand + 2.\nGain theaxe:Spin equal to half of your hand size~~-  this turn -~~ .","mod":"The Axe"},{"id":"TheAxe:Desolator","name":"Desolator","color":"Axe_color","rarity":"Uncommon","type":"Attack","cost":"2","description":"Deal 12 (16) damage.\nApply theaxe:Slow to the enemy.","mod":"The Axe"},{"id":"TheAxe:DevourMangoes","name":"Devour Mangoes","color":"Axe_color","rarity":"Uncommon","type":"Skill","cost":"X","description":"Apply 4 theaxe:Bloodlust X (+1) times.","mod":"The Axe"},{"id":"TheAxe:EtherealBlade","name":"Ethereal Blade","color":"Axe_color","rarity":"Uncommon","type":"Skill","cost":"2","description":"Apply 2 (3) theaxe:Bloodlust for each card in your hand.","mod":"The Axe"},{"id":"TheAxe:GutPunch","name":"Gut Punch","color":"Axe_color","rarity":"Uncommon","type":"Attack","cost":"1","description":"Deal 4 (6) damage.\nApply theaxe:Bloodlust equal to unblocked damage dealt.","mod":"The Axe"},{"id":"TheAxe:HandOfMidas","name":"Hand Of Midas","color":"Axe_color","rarity":"Uncommon","type":"Skill","cost":"","description":"theaxe:Item.\nGain 6 (8) Gold at the end of combat.\nOn Exhaust, gain half as much instead.","mod":"The Axe"},{"id":"TheAxe:ISaidGoodDaySir","name":"I Said Good Day Sir!","color":"Axe_color","rarity":"Uncommon","type":"Skill","cost":"2","description":"The enemy instantly attacks you for 1 damage 3 (4) times.","mod":"The Axe"},{"id":"TheAxe:ItsMogulTime","name":"It's Mogul Time","color":"Axe_color","rarity":"Uncommon","type":"Power","cost":"1","description":" (Innate.)\nWhenever an attack deals unblocked damage, apply 1 theaxe:Bloodlust.","mod":"The Axe"},{"id":"TheAxe:KillSteal","name":"Kill Steal","color":"Axe_color","rarity":"Uncommon","type":"Attack","cost":"1","description":"Deal 8 (11) damage.\nGain 1 theaxe:Metallicize.","mod":"The Axe"},{"id":"TheAxe:MagicWand","name":"Magic Wand","color":"Axe_color","rarity":"Uncommon","type":"Skill","cost":"","description":"theaxe:Item.\nHeal 4 (6) HP at the end of combat.\nOn Exhaust, heal half as much instead.","mod":"The Axe"},{"id":"TheAxe:OneManArmy","name":"One Man Army","color":"Axe_color","rarity":"Uncommon","type":"Skill","cost":"2","description":"Gain 10 (12) Block.\nGain 2 (3) theaxe:Spin.","mod":"The Axe"},{"id":"TheAxe:Outplayed","name":"Outplayed","color":"Axe_color","rarity":"Uncommon","type":"Skill","cost":"X","description":"Draw X times 2 (3) cards. Discard these cards except those tied for the highest cost. Gain [E] equal to that cost. Exhaust.","mod":"The Axe"},{"id":"TheAxe:OverwhelmingBlink","name":"Overwhelming Blink","color":"Axe_color","rarity":"Uncommon","type":"Attack","cost":"1","description":"Deal 3 (4) damage and apply 1 (2) Vulnerable to ALL enemies.\nDraw 1 card.","mod":"The Axe"},{"id":"TheAxe:PhaseBoots","name":"Phase Boots","color":"Axe_color","rarity":"Uncommon","type":"Attack","cost":"0","description":"Deal 2 (3) damage.\nGain 1 (2) Block.\nDraw a card.","mod":"The Axe"},{"id":"TheAxe:Push","name":"Push","color":"Axe_color","rarity":"Uncommon","type":"Power","cost":"1 (0)","description":"At the end of your turn, deal damage equal to your theaxe:Spin to ALL enemies.","mod":"The Axe"},{"id":"TheAxe:ReactionTime","name":"Reaction Time","color":"Axe_color","rarity":"Uncommon","type":"Power","cost":"2 (1)","description":"When you are attacked, draw 1 card.","mod":"The Axe"},{"id":"TheAxe:Reposition","name":"Reposition","color":"Axe_color","rarity":"Uncommon","type":"Skill","cost":"1","description":"Gain 5 (8) Block.\nNext turn, gain [E]  and draw 1 additional card.","mod":"The Axe"},{"id":"TheAxe:ShivasGuard","name":"Shiva's Guard","color":"Axe_color","rarity":"Uncommon","type":"Skill","cost":"2","description":"Gain 11 (14) Block.\nApply 1 (2) Weak to ALL enemies.","mod":"The Axe"},{"id":"TheAxe:TankRoshan","name":"Tank Roshan","color":"Axe_color","rarity":"Uncommon","type":"Skill","cost":"2","description":"Gain 11 (15) Block.\nNext turn, gain [E] [E].","mod":"The Axe"},{"id":"TheAxe:TowerDive","name":"Tower Dive","color":"Axe_color","rarity":"Uncommon","type":"Skill","cost":"2","description":"Apply 7 (9) theaxe:Bloodlust.\nExhaust any number of cards in your hand. Gain 2 (3) Block for each card Exhausted.","mod":"The Axe"},{"id":"TheAxe:TunnelVision","name":"Tunnel Vision","color":"Axe_color","rarity":"Uncommon","type":"Attack","cost":"2","description":"Deal 21 (28) damage.\nEnd your turn.","mod":"The Axe"},{"id":"TheAxe:UrnOfShadows","name":"Urn Of Shadows","color":"Axe_color","rarity":"Uncommon","type":"Attack","cost":"1","description":"Retain. Deal 4 (7) damage. When you play another card with this in hand, increase this card's damage by 1 this combat.","mod":"The Axe"},{"id":"TheAxe:VladmirsOffering","name":"Vladmir's Offering","color":"Axe_color","rarity":"Uncommon","type":"Skill","cost":"1 (0)","description":"Add 2 random theaxe:Item cards to your hand. Exhaust.","mod":"The Axe"},{"id":"TheAxe:AeonDisk","name":"Aeon Disk","color":"Axe_color","rarity":"Rare","type":"Skill","cost":"","description":"theaxe:Item.\nWhen you lose HP, Exhaust this card.\nOn Exhaust, gain 1 Buffer. (When drawn, draw 1 card.)\n","mod":"The Axe"},{"id":"TheAxe:BlackKingBar","name":"Black King Bar","color":"Axe_color","rarity":"Rare","type":"Skill","cost":"1","description":" (Retain.)\nRemove all debuffs. Gain 2 Artifact. Exhaust.","mod":"The Axe"},{"id":"TheAxe:CarryTheTeam","name":"Carry The Team","color":"Axe_color","rarity":"Rare","type":"Power","cost":"2","description":"At the start of your turn, add a card from your draw pile to your hand ( and gain [E]).","mod":"The Axe"},{"id":"TheAxe:Cheese","name":"Cheese","color":"Axe_color","rarity":"Rare","type":"Skill","cost":"3 (2)","description":"Retain.\nDraw 1 fewer card next turn. Take another turn after this one.\nEnd your turn.\nExhaust.","mod":"The Axe"},{"id":"TheAxe:CounterAStove","name":"Counter A Stove","color":"Axe_color","rarity":"Rare","type":"Attack","cost":"X","description":"Deal damage equal to the sum of your theaxe:Metallicize, theaxe:Plated_Armor, and Block X (+1) times.","mod":"The Axe"},{"id":"TheAxe:CullingBlade","name":"Culling Blade","color":"Axe_color","rarity":"Rare","type":"Attack","cost":"1","description":"Deal 5 (6) Damage.\nThen, instantly kill the enemy if they have less than 20 (30) health.\nIf you do, theaxe:Refresh. Exhaust.","mod":"The Axe"},{"id":"TheAxe:Dagon","name":"Dagon","color":"Axe_color","rarity":"Rare","type":"Attack","cost":"1","description":" (Retain.)\nDeal 10 damage.\nDeals bonus damage equal to the enemy's theaxe:Bloodlust.\nExhaust.","mod":"The Axe"},{"id":"TheAxe:FinishedFarming","name":"Finished Farming","color":"Axe_color","rarity":"Rare","type":"Power","cost":"1","description":"At the end of your turn, gain 1 (2) Block for each card you Retain.","mod":"The Axe"},{"id":"TheAxe:GoodkindLook","name":"Goodkind, Look!","color":"Axe_color","rarity":"Rare","type":"Attack","cost":"2","description":"Deal 10 (13) damage.\nIf Fatal, start each combat with 1 more theaxe:Spin.\nExhaust.","mod":"The Axe"},{"id":"TheAxe:LiterallyNoDamage","name":"Literally No Damage","color":"Axe_color","rarity":"Rare","type":"Skill","cost":"3","description":"ALL enemies lose 99 Strength this turn.\nGain 4 (6) theaxe:Spin.\nExhaust.","mod":"The Axe"},{"id":"TheAxe:LotusOrb","name":"Lotus Orb","color":"Axe_color","rarity":"Rare","type":"Skill","cost":"2","description":"Gain 16 (20) Block.\nGain 1 (2) Artifact.\nExhaust.","mod":"The Axe"},{"id":"TheAxe:Mekansm","name":"Mekansm","color":"Axe_color","rarity":"Rare","type":"Skill","cost":"1","description":"Gain 8 (10) Block.\nExhaust 1 (2) card (cards) in your draw pile.","mod":"The Axe"},{"id":"TheAxe:RedMistForm","name":"Red Mist Form","color":"Axe_color","rarity":"Rare","type":"Power","cost":"3","description":"Whenever you gain theaxe:Spin, gain 2 (3) extra.","mod":"The Axe"},{"id":"TheAxe:RefresherOrb","name":"Refresher Orb","color":"Axe_color","rarity":"Rare","type":"Skill","cost":"1 (0)","description":"Exhaust your hand.\ntheaxe:Refresh any Exhausted theaxe:Item cards.\nExhaust.","mod":"The Axe"},{"id":"TheAxe:SangeAndYasha","name":"Sange And Yasha","color":"Axe_color","rarity":"Rare","type":"Skill","cost":"","description":"theaxe:Item.\nOn ~~- every other  -~~ Retain, gain 1 Strength and 1 Spin. On Exhaust, gain 2 of your choice.","mod":"The Axe"},{"id":"TheAxe:Satanic","name":"Satanic","color":"Axe_color","rarity":"Rare","type":"Attack","cost":"1","description":"Deal 6 (10) damage.\nGain [E].\nDraw 1 card.\nAdd a Dazed to your hand.","mod":"The Axe"},{"id":"TheAxe:SellForBuyback","name":"Sell For Buyback","color":"Axe_color","rarity":"Rare","type":"Power","cost":"1","description":"At the end of your turn, you may Exhaust up to 1 (2) card (cards) in your hand.","mod":"The Axe"},{"id":"TheAxe:SupportTheTeam","name":"Support The Team","color":"Axe_color","rarity":"Rare","type":"Power","cost":"1","description":"Increase the number of cards you can hold by 1 (2).","mod":"The Axe"},{"id":"TheAxe:YouGetNothing","name":"You Get Nothing","color":"Axe_color","rarity":"Rare","type":"Power","cost":"1","description":" (Innate. ) The first time you lose HP each turn, all enemies lose 1 Strength.","mod":"The Axe"}],"relics":[{"id":"TheAxe:BladeMail","name":"Blade Mail","tier":"Starter","pool":"Axe_color","description":"Gain 2 theaxe:Spin at the start of combat.","flavorText":"A razor-sharp coat of mail, it is the choice of selfless martyrs in combat. Or skilled show-offs.","mod":"The Axe"},{"id":"TheAxe:CloakOfFlames","name":"Cloak Of Flames","tier":"Common","pool":"Axe_color","description":"When you are attacked, apply 1 theaxe:Bloodlust to ALL enemies.","flavorText":"A very fine cloak that plays host to an overly-protective living flame.","mod":"The Axe"},{"id":"TheAxe:AegisOfTheImmortal","name":"Aegis Of The Immortal","tier":"Uncommon","pool":"Axe_color","description":"The first time you would die each combat, heal 4 HP instead.","flavorText":"The Immortal was said to own a shield that protected him from death itself.","mod":"The Axe"},{"id":"TheAxe:Vanguard","name":"Vanguard","tier":"Uncommon","pool":"Axe_color","description":"Gain 2 theaxe:Malleable at the start of combat.","flavorText":"A powerful shield that defends its wielder from even the most vicious of attacks.","mod":"The Axe"},{"id":"TheAxe:HeavensHalberd","name":"Heaven's Halberd","tier":"Rare","pool":"Axe_color","description":"Every 5 turns, prevent the next time you would lose HP.","flavorText":"This halberd moves with the speed of a smaller weapon, allowing the bearer to win duels that a heavy edge would not.","mod":"The Axe"},{"id":"TheAxe:TricksterCloak","name":"Trickster Cloak","tier":"Rare","pool":"Axe_color","description":"At the start of combat, choose 1 of 2 theaxe:Item cards to add to your hand.","flavorText":"A fantastic garment immediately misplaced by its creator upon completion.","mod":"The Axe"},{"id":"TheAxe:GoodkindsPrestige","name":"Goodkind's Prestige","tier":"Special","pool":"Axe_color","description":"Gain theaxe:Spin at the start of combat.","flavorText":"Axe's reputation precedes him, thanks to his Bard companion.","mod":"The Axe"},{"id":"TheAxe:DivineRapier","name":"Divine Rapier","tier":"Boss","pool":"Axe_color","description":"Gain [E] at the start of each turn. Start combats with 3 Unplayable Retaining Curses added to your opening hand.","flavorText":"So powerful, it cannot have a single owner.","mod":"The Axe"},{"id":"TheAxe:GiantsRing","name":"Giant's Ring","tier":"Boss","pool":"Axe_color","description":"Draw 1 additional card and add a Dazed to your hand each turn.","flavorText":"Prized procurement of an otherwise unremarkable ruler of Elze who abdicated his position and vanished.","mod":"The Axe"},{"id":"TheAxe:HeartOfTarrasque","name":"Heart of Tarrasque","tier":"Boss","pool":"Axe_color","description":"Replaces Blade Mail. Start each combat with 5 theaxe:Metallicize and 3 Regen.","flavorText":"Preserved heart of an extinct monster, it bolsters the bearer's fortitude.","mod":"The Axe"},{"id":"TheAxe:Bloodstone","name":"Bloodstone","tier":"Shop","pool":"Axe_color","description":"theaxe:Bloodlust no longer decrements when enemies damage you.","flavorText":"The Bloodstone's bright ruby color is unmistakable on the battlefield, as the owner seems to have infinite vitality and spirit.","mod":"The Axe"}],"potions":[],"creatures":[{"id":"TheAxe","name":"The Axe","type":"Player","minHP":"78","maxHP":"78","mod":"The Axe"}],"keywords":[{"name":"Multiword Keyword","description":"Make sure the first element in the NAMES is the same as your PROPER_NAME. The rest should use _ to replace spaces. In card text, you'll use the underscore versions.","mod":"The Axe"},{"name":"Plated Armor","description":"At the end of your turn, gain Block. Receiving unblocked attack damage reduces Plated Armor by 1.","mod":"The Axe"},{"name":"This is displayed in the tooltip.","description":"This is displayed in the tooltip. Note, spaces are not allowed in NAMES. For multi-word keywords, see the next one.","mod":"The Axe"},{"name":"Bloodlust","description":"Bloodlusted creatures lose HP at the start of their turn. Bloodlust is reduced by a third when the creature deals unblocked damage.","mod":"The Axe"},{"name":"Blur","description":"Block is not removed at the start of your next turn.","mod":"The Axe"},{"name":"Buffer","description":"The next time you lose HP, reduce the HP loss to 0.","mod":"The Axe"},{"name":"Item","description":"Items are Unplayable cards with Retain that have a passive effect in the hand and provide another effect on xhaust.","mod":"The Axe"},{"name":"Malleable","description":"Upon receiving attack damage, gain Block. Block gain increases by 1 each time Malleable is triggered. Resets at the start of your turn.","mod":"The Axe"},{"name":"Metallicize","description":"Gain Block at the end of your turn.","mod":"The Axe"},{"name":"Refresh","description":"Add a copy of this card to your hand next turn.","mod":"The Axe"},{"name":"Slow","description":"Whenever you play a card, the enemy receives 10% more damage from attacks this turn.","mod":"The Axe"},{"name":"Spin","description":"When receiving Attack damage, deal damage equal to Spin to ALL enemies.","mod":"The Axe"},{"name":"Vigor","description":"Your next attack deals extra damage.","mod":"The Axe"}],"mods":[{"name":"The Axe","version":"0.3.0","authors":["Axelrod777"],"credits":"","description":"Adds Axe from Dota 2 as a playable character.\n- Features 75 new cards with unique art, including custom-made art and art from Dota.\n\n- Accumulate Spin to retaliate against groups of enemies.\n- Stack Bloodlust on the enemy to wear them down until they damage you.\n- Collect Item cards, which provide passive benefit in the hand.\n\nCredits:\n- Mod designed and programmed by Axelrod777. Discord: Axelrod#5084.\n- Featuring character and card art by jdeg.jpg on Instagram. Discord: JDegs#9781.\n- Featuring other art by Jangirl#3025 on Discord.\n- Credit to Jalcober, propen, and burga boy for some Steam Workshop art.\n- Special thanks to the Slay The Spire Discord's modding channel for all their help.\n- Axe, Dota, Artifact, and Underlords belong to Valve Corporation.\n\nComing soon: More potions, more custom art, and balance updates.\nPlaytesting build. Not intended for public release.\nSend balance and feature suggestions to Axelrod#5084 on Discord.","mts_version":"3.25.2","sts_version":"03-07-2022","dependencies":["basemod","stslib"],"optional_dependencies":[]}]}