{"cards":[{"id":"skulmod:CuteLittleSkulls","name":"Cute Little Skulls","color":"Quartz_purple","rarity":"Basic","type":"Attack","cost":"2","description":"Deal 6 (9) damage.\nskulmod:Bonepile 2 (4).","mod":"skulmod"},{"id":"skulmod:Defend","name":"Defend","color":"Quartz_purple","rarity":"Basic","type":"Skill","cost":"1","description":"Gain 5 (8) Block.","mod":"skulmod"},{"id":"skulmod:LetsKnitTogether","name":"Let's...Knit...","color":"Quartz_purple","rarity":"Basic","type":"Skill","cost":"1","description":"You and the target gain 5 (8) Block.\nskulmod:Bonepile 3 (4).","mod":"skulmod"},{"id":"skulmod:LittleBoneSkull","name":"Little Bone","color":"Quartz_purple","rarity":"Basic","type":"Power","cost":"","description":"skulmod:Passive: Take 1 less damage.\nskulmod:Bonepile: Gain 2 Block.\nskulmod:Swap: Gain [E] [E] .","mod":"skulmod"},{"id":"skulmod:Strike","name":"Strike","color":"Quartz_purple","rarity":"Basic","type":"Attack","cost":"1","description":"Deal 6 (9) damage.","mod":"skulmod"},{"id":"skulmod:AbyssSpike","name":"Abyss Spike","color":"Quartz_purple","rarity":"Special","type":"Attack","cost":"0","description":"Deal 4 (6) damage.\nBecomes Abyss Orb (+) in your hand.","mod":"skulmod"},{"id":"skulmod:Acceleration","name":"Acceleration","color":"Quartz_purple","rarity":"Special","type":"Skill","cost":"","description":"Unplayable.\nWhen you draw this card, draw 2 (3) cards and discard this. Next time, exhaust this instead.","mod":"skulmod"},{"id":"skulmod:DistantHope","name":"Ascender's Bane","color":"Quartz_purple","rarity":"Special","type":"Curse","cost":"","description":"Unplayable.\nEthereal.\nCannot be removed from your deck.","mod":"skulmod"},{"id":"skulmod:Awakening","name":"Awakening","color":"Quartz_purple","rarity":"Special","type":"Skill","cost":"2 (1)","description":"skulmod:Bleached. Ethereal.\nDeal 3 non-attack damage 0 times, equal to your Vigor, and remove it.","mod":"skulmod"},{"id":"skulmod:BoarChase","name":"Boar Chase","color":"Quartz_purple","rarity":"Special","type":"Attack","cost":"0","description":"Retain. skulmod:Grapple.\nDeal 2 damage.\nExhaust.","mod":"skulmod"},{"id":"skulmod:BullFight","name":"Bull Fight","color":"Quartz_purple","rarity":"Special","type":"Attack","cost":"0","description":"Retain. skulmod:Grapple.\nDeal 2 (4) damage.\nExhaust.","mod":"skulmod"},{"id":"skulmod:CeremonialWeapon","name":"Ceremonial Weapon","color":"Quartz_purple","rarity":"Special","type":"Skill","cost":"","description":"Create a new  (Upgraded) Unrivaled Strike on the left of your hand.","mod":"skulmod"},{"id":"skulmod:Cannonfire","name":"Fire!","color":"Quartz_purple","rarity":"Special","type":"Attack","cost":"0","description":"skulmod:Bleached.\nDeal 1 damage (2 times).\nPurge.","mod":"skulmod"},{"id":"skulmod:GreenDragonCrescent","name":"Green Dragon Crescent","color":"Quartz_purple","rarity":"Special","type":"Skill","cost":"","description":"The Unrivaled Strike will skulmod:Bonepile 3 (4) times.","mod":"skulmod"},{"id":"skulmod:Hibernation","name":"Hibernation","color":"Quartz_purple","rarity":"Special","type":"Skill","cost":"1","description":"Retain. skulmod:Bleached.\nApply 10 (16) skulmod:Frozen.\nPurge.","mod":"skulmod"},{"id":"skulmod:HydraSlam","name":"Hydra Slam","color":"Quartz_purple","rarity":"Special","type":"Attack","cost":"0","description":"Retain. skulmod:Grapple.\nDeal 2 (3) damage.\nExhaust.","mod":"skulmod"},{"id":"skulmod:FakeHydraSlam","name":"Hydra Slam","color":"Quartz_purple","rarity":"Special","type":"Attack","cost":"0","description":"Retain. skulmod:Grapple.\nDeal 2 (3) damage~~-  to ALL enemies -~~ .\nExhaust.","mod":"skulmod"},{"id":"skulmod:LaughingArrow","name":"Laughing Arrow","color":"Quartz_purple","rarity":"Special","type":"Skill","cost":"","description":"Switch the Unrivaled Strike between dealing damage and gaining Block.","mod":"skulmod"},{"id":"skulmod:LionHunt","name":"Lion Hunt","color":"Quartz_purple","rarity":"Special","type":"Attack","cost":"0","description":"Retain. skulmod:Grapple.\nDeal 2 (3) damage.\nExhaust.","mod":"skulmod"},{"id":"skulmod:LoadedDice","name":"Loaded Dice","color":"Quartz_purple","rarity":"Special","type":"Skill","cost":"0","description":"Ethereal. Purge.\nDraw 1 (2) card (cards).\nYour next attack this turn deals 7 (14)% more damage.","mod":"skulmod"},{"id":"skulmod:MatterOfState","name":"Matter Of State","color":"Quartz_purple","rarity":"Special","type":"Skill","cost":"","description":"Discard the Unrivaled Strike to gain 10 (15) Block. If it was Blocking, gain 10 (15) Block next turn.","mod":"skulmod"},{"id":"skulmod:ParasolCharge","name":"Parasol Charge","color":"Quartz_purple","rarity":"Special","type":"Skill","cost":"","description":"The Unrivaled Strike deals 5 (8) more damage.\nIf it was Blocking, double this.","mod":"skulmod"},{"id":"skulmod:PeerlessBlow","name":"Peerless Blow","color":"Quartz_purple","rarity":"Special","type":"Skill","cost":"","description":"The Unrivaled Strike hits one enemy, costs 1 more, and refunds double its cost.\nIf it was Blocking, gain 2 (3) Temporary Strength.","mod":"skulmod"},{"id":"skulmod:RecallHead","name":"Recall Head","color":"Quartz_purple","rarity":"Special","type":"Skill","cost":"0","description":"Gain 5 (8) Block.\nChannel 2 (3) skulmod:Empty_Head. \nBecomes Throw Head (+) in your hand.","mod":"skulmod"},{"id":"skulmod:SixGeneralsFivePasses","name":"Six Generals, Five Passes","color":"Quartz_purple","rarity":"Special","type":"Skill","cost":"","description":"Exhaust the Unrivaled Strike to draw 2 (3) cards. If it was Blocking, draw 3 more.","mod":"skulmod"},{"id":"skulmod:BomberSkull","name":"Skeleton-Bomber","color":"Quartz_purple","rarity":"Special","type":"Power","cost":"","description":"Given that he's not supposed to be exposed like this, he's a little afraid right now.","mod":"skulmod"},{"id":"skulmod:StrategyBook","name":"Strategy Book","color":"Quartz_purple","rarity":"Special","type":"Skill","cost":"0","description":"Retain. Exhaust.\nYour Leftmost Unrivaled Strike gains 1 of 3 effects, otherwise make one.","mod":"skulmod"},{"id":"skulmod:StrengthOf10K","name":"Strength of 10,000","color":"Quartz_purple","rarity":"Special","type":"Skill","cost":"","description":"The Unrivaled Strike will apply Strength 1 (2) more time (times).","mod":"skulmod"},{"id":"skulmod:TigerGeneral","name":"Tiger General","color":"Quartz_purple","rarity":"Special","type":"Skill","cost":"","description":"Exhaust the Unrivaled Strike to gain 2 (3) Strength. If it was Blocking, gain double.","mod":"skulmod"},{"id":"skulmod:UnrivaledStrike","name":"Unrivaled Strike","color":"Quartz_purple","rarity":"Special","type":"Attack","cost":"1","description":" Deal 4 (6) damage to ALL enemies.","mod":"skulmod"},{"id":"skulmod:AbyssOrb","name":"Abyss Orb","color":"Quartz_purple","rarity":"Common","type":"Attack","cost":"1","description":"Ethereal.\nDeal 4 (6) damage.\nBecomes Abyss Spike (+) in your hand.","mod":"skulmod"},{"id":"skulmod:Bribe","name":"Bribe","color":"Quartz_purple","rarity":"Common","type":"Skill","cost":"0","description":"skulmod:Pay 20 (10) Gold.\nskulmod:Bonepile 2.\nDraw 1 card.\nExhaust.","mod":"skulmod"},{"id":"skulmod:BrittleBones","name":"Brittle Bones","color":"Quartz_purple","rarity":"Common","type":"Power","cost":"0","description":"Gain 2 (3) Frail.\nGain 4 (6) Thorns.","mod":"skulmod"},{"id":"skulmod:FireArrow","name":"Fire Arrow","color":"Quartz_purple","rarity":"Common","type":"Attack","cost":"1","description":"Deal 2 (3) damage.\nApply 4 (6) skulmod:Burn. If the target is already Burned, remove it and gain half as much Vigor instead.","mod":"skulmod"},{"id":"skulmod:Hunt","name":"Hunt","color":"Quartz_purple","rarity":"Common","type":"Skill","cost":"","description":"Unplayable.\nWhen drawn, play the top card of your draw pile and discard (replace)  (it with) a random card (in your hand).","mod":"skulmod"},{"id":"skulmod:HunterSkull","name":"Hunter","color":"Quartz_purple","rarity":"Common","type":"Power","cost":"","description":"skulmod:Passive: Attacks Channel an skulmod:Arrow.\nskulmod:Bonepile: Channel 1 skulmod:Arrow.\nskulmod:Swap: Gain an empty orb slot.","mod":"skulmod"},{"id":"skulmod:PatternRecognition","name":"Pattern  Recognition","color":"Quartz_purple","rarity":"Common","type":"Skill","cost":"1","description":"Apply 2 (3) Weak.\nChannel 2 (3) skulmod:Empty_Head.\nExhaust.","mod":"skulmod"},{"id":"skulmod:PowerStrike","name":"Power Strike","color":"Quartz_purple","rarity":"Common","type":"Attack","cost":"3","description":"Deal 18 damage.\nCosts 1 (2) less when skulmod:Charged.","mod":"skulmod"},{"id":"skulmod:PrepareForBoarding","name":"Prepare For Boarding!","color":"Quartz_purple","rarity":"Common","type":"Skill","cost":"0","description":"Discard 1 (up) card (to)  (2 cards) to gain 8 (10) Block (for each).","mod":"skulmod"},{"id":"skulmod:ShieldBash","name":"Shield Bash","color":"Quartz_purple","rarity":"Common","type":"Attack","cost":"1","description":"Deal 4 (7) damage.\nGain 4 (7) Block.","mod":"skulmod"},{"id":"skulmod:ShieldSmash","name":"Shield Smash","color":"Quartz_purple","rarity":"Common","type":"Attack","cost":"1","description":"Deal 0 damage, based on your current Block.\nskulmod:Bonepile 1 (3).","mod":"skulmod"},{"id":"skulmod:SiegeShot","name":"Siege Shot","color":"Quartz_purple","rarity":"Common","type":"Attack","cost":"1","description":"Deal 2 (3) damage.\nApply that much Lock-On.","mod":"skulmod"},{"id":"skulmod:ShieldSkull","name":"Skeleton-Shield","color":"Quartz_purple","rarity":"Common","type":"Power","cost":"","description":"skulmod:Passive: Dexterity doubles as Thorns.\nskulmod:Bonepile: Channel 1 skulmod:Barrier.\nskulmod:Swap: Gain 5 Dexterity until next turn.","mod":"skulmod"},{"id":"skulmod:SlotMachine","name":"Slot Machine","color":"Quartz_purple","rarity":"Common","type":"Skill","cost":"1 (0)","description":"skulmod:Bonepile  between 0 and 4 (5) times.","mod":"skulmod"},{"id":"skulmod:StartTheMatch","name":"Start the Match!","color":"Quartz_purple","rarity":"Common","type":"Skill","cost":"0","description":"Innate.\nskulmod:Bonepile 2 (4).\nExhaust.","mod":"skulmod"},{"id":"skulmod:StarterKit","name":"Starter Kit","color":"Quartz_purple","rarity":"Common","type":"Skill","cost":"1","description":"Innate.\nGain 7 (10) Gold.\nApply 7 (10) skulmod:Ripped_Pocket.\nExhaust.","mod":"skulmod"},{"id":"skulmod:Thief","name":"Street Thievery","color":"Quartz_purple","rarity":"Common","type":"Attack","cost":"1","description":"Deal 4 damage.\nGain 5 (7) Gold.\nAfter gaining 24 Gold, also gain 6 Block.","mod":"skulmod"},{"id":"skulmod:PowerCharge","name":"Striking Charge","color":"Quartz_purple","rarity":"Common","type":"Skill","cost":"1","description":"Gain 3 (4) Vigor.\nskulmod:Bonepile 3 (4).","mod":"skulmod"},{"id":"skulmod:ThrowHead","name":"Throw Head","color":"Quartz_purple","rarity":"Common","type":"Attack","cost":"0","description":"Deal 3 (6) damage.\nChannel 2 (3) skulmod:Empty_Head.\nBecomes Recall Head (+) in your discard pile.","mod":"skulmod"},{"id":"skulmod:WarriorSkull","name":"Warrior","color":"Quartz_purple","rarity":"Common","type":"Power","cost":"","description":"skulmod:Passive: Gain [E] after playing a Strike.\nskulmod:Bonepile: Gain 1 skulmod:Charge.\nskulmod:Swap: Gain 5 skulmod:Charge.","mod":"skulmod"},{"id":"skulmod:WerewolfSkull","name":"Werewolf","color":"Quartz_purple","rarity":"Common","type":"Power","cost":"","description":"skulmod:Passive: Deal damage equal to your skulmod:Total_Cards when Reshuffling.\nskulmod:Bonepile: Draw and randomly discard 1 card.\nskulmod:Swap: Reshuffle.","mod":"skulmod"},{"id":"skulmod:Backroll","name":"Backroll","color":"Quartz_purple","rarity":"Uncommon","type":"Skill","cost":"1","description":"skulmod:Pay 20 (10) Gold.\nGain 8 (12) Block.\nApply 6 (10) skulmod:Ripped_Pocket.","mod":"skulmod"},{"id":"skulmod:Backstab","name":"Backstab","color":"Quartz_purple","rarity":"Uncommon","type":"Attack","cost":"1","description":"Deal 5 (8) damage, then gain the same amount of Gold up to 15 (25).","mod":"skulmod"},{"id":"skulmod:BackstepShot","name":"Backstep Shot","color":"Quartz_purple","rarity":"Uncommon","type":"Skill","cost":"1","description":"Gain 7 (11) Block.\nChannel 1 (2) skulmod:Arrow (Arrows).","mod":"skulmod"},{"id":"skulmod:BirthOfAHero","name":"Birth Of A Hero","color":"Quartz_purple","rarity":"Uncommon","type":"Skill","cost":"1","description":"Whenever you play an Attack this turn, gain 3 (5) Block.\nAdd a random skulmod:Grapple to your hand.","mod":"skulmod"},{"id":"skulmod:Blackjack","name":"Black Jack","color":"Quartz_purple","rarity":"Uncommon","type":"Skill","cost":"1 (0)","description":"Add 2 Loaded Dice to your hand.","mod":"skulmod"},{"id":"skulmod:BombsAway","name":"Bombs Away!","color":"Quartz_purple","rarity":"Uncommon","type":"Attack","cost":"1","description":"Deal 8 (10) damage and gain Block equal to the unblocked damage dealt.\n~~- Exhaust. -~~ ","mod":"skulmod"},{"id":"skulmod:ChainStrike","name":"Chain Strike","color":"Quartz_purple","rarity":"Uncommon","type":"Attack","cost":"0","description":"Deal 4 (6) damage.\nReturn this card to your hand whenever you play a Strike except Chain Strike.","mod":"skulmod"},{"id":"skulmod:ClownSkull","name":"Clown","color":"Quartz_purple","rarity":"Uncommon","type":"Power","cost":"","description":"skulmod:Passive: Your first card each turn costs 0.\nskulmod:Bonepile: Add an skulmod:Imitation to your hand.\nskulmod:Swap: Bonepile 2.","mod":"skulmod"},{"id":"skulmod:DarkPaladinSkull","name":"Dark Paladin","color":"Quartz_purple","rarity":"Uncommon","type":"Power","cost":"","description":"skulmod:Passive: Fully Blocking grants 4 skulmod:Oblivion.\nskulmod:Bonepile: skulmod:Grit 2.\nskulmod:Swap: Gain 8 Oblivion.","mod":"skulmod"},{"id":"skulmod:DarkSanctuary","name":"Dark Sanctuary","color":"Quartz_purple","rarity":"Uncommon","type":"Skill","cost":"0","description":"Take 4 damage 3 (4) times.\nGain 24 (32) Block.","mod":"skulmod"},{"id":"skulmod:DarkWave","name":"Dark Wave","color":"Quartz_purple","rarity":"Uncommon","type":"Skill","cost":"X","description":"Gain 4X (5X) Block.\nGain 2X (4X) skulmod:Oblivion.","mod":"skulmod"},{"id":"skulmod:DirtySmash","name":"Dirty Smash","color":"Quartz_purple","rarity":"Uncommon","type":"Attack","cost":"2","description":"Deal 12 (16) damage.\nWhile in Wrath, deal damage again and exit Wrath.","mod":"skulmod"},{"id":"skulmod:Dominate","name":"Dominate","color":"Quartz_purple","rarity":"Uncommon","type":"Attack","cost":"1","description":"Deal 5 (8) damage.\nApply 1 (2) Vulnerable.","mod":"skulmod"},{"id":"skulmod:DoomedDance","name":"Doomed Dance","color":"Quartz_purple","rarity":"Uncommon","type":"Power","cost":"1","description":"Gain 5 (7) Block each turn. If you take unblocked damage, that Block becomes Poison (Constrict).","mod":"skulmod"},{"id":"skulmod:IAmTheSea","name":"Everwinter","color":"Quartz_purple","rarity":"Uncommon","type":"Power","cost":"1","description":" (Innate.)\nChannel 1 skulmod:Blizzard\nChannel 1 skulmod:Blizzard at the start of the turn.","mod":"skulmod"},{"id":"skulmod:TheFifthMeteor","name":"Full Charge","color":"Quartz_purple","rarity":"Uncommon","type":"Skill","cost":"1","description":"Gain 1 (2) Focus.\nGain 1 (2) Temporary Focus.\nExhaust.","mod":"skulmod"},{"id":"skulmod:GamblerSkull","name":"Gambler","color":"Quartz_purple","rarity":"Uncommon","type":"Power","cost":"","description":"skulmod:Passive: skulmod:Gamble when you play cards.\nskulmod:Bonepile: Shuffle a Loaded Dice into your draw pile.\nskulmod:Swap: Passive chance doubles this turn.","mod":"skulmod"},{"id":"skulmod:GreatWarlockSkull","name":"Great Warlock","color":"Quartz_purple","rarity":"Uncommon","type":"Power","cost":"","description":"skulmod:Passive: Attack damage applies Concentration.\nskulmod:Bonepile: Reduce ALL skulmod:Concentration.\nskulmod:Swap: Remove ALL Concentration.","mod":"skulmod"},{"id":"skulmod:LowerTheAnchor","name":"Lower The Anchor!","color":"Quartz_purple","rarity":"Uncommon","type":"Skill","cost":"0","description":"Discard a card to skulmod:Bonepile 3 (4).","mod":"skulmod"},{"id":"skulmod:MageSkull","name":"Mage","color":"Quartz_purple","rarity":"Uncommon","type":"Power","cost":"","description":"skulmod:Passive: Skills grant 2 Vigor.\nskulmod:Bonepile: Apply skulmod:Burn randomly.\nskulmod:Swap: Create an Awakening.","mod":"skulmod"},{"id":"skulmod:Momentum","name":"Momentum Strike","color":"Quartz_purple","rarity":"Uncommon","type":"Attack","cost":"1","description":"Deal 5 damage.\nDeals 2 (3) more damage each time it's drawn or discarded.","mod":"skulmod"},{"id":"skulmod:OneInchPunch","name":"One-Inch Punch","color":"Quartz_purple","rarity":"Uncommon","type":"Skill","cost":"2","description":"Become Entangled unless you're in Wrath.\nskulmod:Bonepile 6 (8).\nDraw 1 card.","mod":"skulmod"},{"id":"skulmod:PettyThiefSkull","name":"Petty Thief","color":"Quartz_purple","rarity":"Uncommon","type":"Power","cost":"","description":"skulmod:Passive: Gaining Gold randomly deals that much damage.\nskulmod:Bonepile: Gain 4 Gold.\nskulmod:Swap: Block damage with twice as much Gold this turn.","mod":"skulmod"},{"id":"skulmod:PiercingShot","name":"Piercing Shot","color":"Quartz_purple","rarity":"Uncommon","type":"Attack","cost":"1","description":"Target loses 4 (6) HP.\nThis HP loss scales as damage.\nExhaust.","mod":"skulmod"},{"id":"skulmod:Predation","name":"Predation","color":"Quartz_purple","rarity":"Uncommon","type":"Attack","cost":"1","description":"Deal 5 (6) damage.\nIf Fatal, raise your Max HP by 5 (8).\nFleeting.","mod":"skulmod"},{"id":"skulmod:PriceOfPower","name":"Price Of Power","color":"Quartz_purple","rarity":"Uncommon","type":"Skill","cost":"1","description":"Gain 2 (4) Block each turn.\nApply 1 (2) Thorns.","mod":"skulmod"},{"id":"skulmod:QuickStep","name":"Quick Step","color":"Quartz_purple","rarity":"Uncommon","type":"Skill","cost":"1","description":"skulmod:Bonepile 1 (2).\nApply 1 (2) Vulnerable.\nApply 1 (2) Weak.","mod":"skulmod"},{"id":"skulmod:RainOfDarts","name":"Rain of Darts","color":"Quartz_purple","rarity":"Uncommon","type":"Attack","cost":"1","description":"Deal 4 damage to ALL enemies between 0 and 3 (5) times.","mod":"skulmod"},{"id":"skulmod:RapidChannel","name":"Rapid Channel","color":"Quartz_purple","rarity":"Uncommon","type":"Skill","cost":"0","description":"Borrow 1 (2) [E] from future turns.\nDraw 1 (2) card (cards).\nExhaust.","mod":"skulmod"},{"id":"skulmod:Reload","name":"Reload","color":"Quartz_purple","rarity":"Uncommon","type":"Skill","cost":"1","description":"Evoke ALL orbs.\nChannel 2 (3) skulmod:Cannonballs.","mod":"skulmod"},{"id":"skulmod:RisingSlash","name":"Rising Slash","color":"Quartz_purple","rarity":"Uncommon","type":"Attack","cost":"2","description":"Deal 7 damage to ALL enemies 1 (2) time (times).\nDraw 1 card.","mod":"skulmod"},{"id":"skulmod:RussianRoulette","name":"Russian Roulette","color":"Quartz_purple","rarity":"Uncommon","type":"Attack","cost":"0","description":"Randomly skulmod:Gamble 2 (3) times, deal 12 (18) damage, or take 6 (9) damage.\nDraw 1 card.","mod":"skulmod"},{"id":"skulmod:ShieldCharge","name":"Shield Charge","color":"Quartz_purple","rarity":"Uncommon","type":"Skill","cost":"2","description":"Gain 10 (14) Block.\nGain 10 (14) Block next turn.","mod":"skulmod"},{"id":"skulmod:ShieldRush","name":"Shield Rush","color":"Quartz_purple","rarity":"Uncommon","type":"Skill","cost":"1","description":"Gain 4 Block 2 (3) times.","mod":"skulmod"},{"id":"skulmod:CooldownReset","name":"Simplicity","color":"Quartz_purple","rarity":"Uncommon","type":"Skill","cost":"0","description":"skulmod:Bonepile 2 (3).\nChannel 2 skulmod:Empty_Head.","mod":"skulmod"},{"id":"skulmod:SurpriseKnives","name":"Surprise Knives!","color":"Quartz_purple","rarity":"Uncommon","type":"Skill","cost":"0","description":"Exhaust the top 2 cards of your draw pile.\nGain [E] equal to their combined cost.\n~~- Exhaust. -~~ ","mod":"skulmod"},{"id":"skulmod:FreeDamage","name":"Tax Strike","color":"Quartz_purple","rarity":"Uncommon","type":"Attack","cost":"1","description":"Deal 5 (8) damage.\nDraw 1 card.\nChannel 1 (2) skulmod:Empty_Head.","mod":"skulmod"},{"id":"skulmod:TheBestOffense","name":"The Best Offense","color":"Quartz_purple","rarity":"Uncommon","type":"Skill","cost":"2 (1)","description":"Convert your Block into Dexterity until your next turn.\nExhaust.","mod":"skulmod"},{"id":"skulmod:GodOfWarSkull","name":"The God of War","color":"Quartz_purple","rarity":"Uncommon","type":"Power","cost":"","description":"*Passive: Skills or 0-cost cards grant skulmod:Tactics.\nBonepile: Gain 1 Tactics.\nSwap: Increase an Unrivaled Strike's damage by 5.","mod":"skulmod"},{"id":"skulmod:ThrowGold","name":"Throw Gold","color":"Quartz_purple","rarity":"Uncommon","type":"Attack","cost":"1","description":"skulmod:Pay 20 (10) Gold.\nDeal 0 damage, equal to the Gold gained this combat.\nExhaust.","mod":"skulmod"},{"id":"skulmod:TwoInOneHand","name":"Two In One Hand","color":"Quartz_purple","rarity":"Uncommon","type":"Skill","cost":"0","description":"Draw 2 (4) cards.\nExhaust.","mod":"skulmod"},{"id":"skulmod:WaitToStrike","name":"Wait To Strike","color":"Quartz_purple","rarity":"Uncommon","type":"Skill","cost":"1","description":"Gain 3 (5) Vigor.\nIf you haven't played an Attack this turn, gain 3 (5) more.","mod":"skulmod"},{"id":"skulmod:AbyssForm","name":"Abyss Form","color":"Quartz_purple","rarity":"Rare","type":"Power","cost":"2","description":"~~- Ethereal. -~~\nskulmod:Concentration damages ALL enemies an additional time when removed.","mod":"skulmod"},{"id":"skulmod:AllInForm","name":"All-In Form","color":"Quartz_purple","rarity":"Rare","type":"Power","cost":"2","description":"~~- Ethereal. -~~\nAt the start of their turn, EVERYONE skulmod:Gambles 2 (3) times.\nIf an enemy wins a Gamble, Gambler does too.","mod":"skulmod"},{"id":"skulmod:AvengerForm","name":"Avenger Form","color":"Quartz_purple","rarity":"Rare","type":"Power","cost":"2","description":"~~- Ethereal. -~~\nGain [E] the first time you take or Block damage during your turn.","mod":"skulmod"},{"id":"skulmod:BerserkerSkull","name":"Berserker","color":"Quartz_purple","rarity":"Rare","type":"Power","cost":"","description":"skulmod:Passive: Losing HP grants as much skulmod:Unshackled. Fatal damage less than Strength heals you to half HP and applies skulmod:Bone_Scream.","mod":"skulmod"},{"id":"skulmod:ChampionSkull","name":"Champion","color":"Quartz_purple","rarity":"Rare","type":"Power","cost":"","description":"skulmod:Passive: skulmod:Counterattack unblocked damage.\nskulmod:Bonepile: Heal the next 3 HP you lose.\nskulmod:Swap: Enter or Exit Wrath.","mod":"skulmod"},{"id":"skulmod:Combo","name":"Combo","color":"Quartz_purple","rarity":"Rare","type":"Attack","cost":"X","description":"Deal 5 (8) damage X times.\nskulmod:Bonepile X times.\nExhaust.","mod":"skulmod"},{"id":"skulmod:DarkCharge","name":"Dark Charge","color":"Quartz_purple","rarity":"Rare","type":"Skill","cost":"1","description":"Draw 1 (2) card (cards).\nGain 12 (16) Block.","mod":"skulmod"},{"id":"skulmod:DarkCross","name":"Dark Cross","color":"Quartz_purple","rarity":"Rare","type":"Attack","cost":"3 (2)","description":"Deal 4 damage 2 (3) times.\nGain Block equal to your Vigor and skulmod:Oblivion.","mod":"skulmod"},{"id":"skulmod:DavyJonesSkull","name":"Davy Jones","color":"Quartz_purple","rarity":"Rare","type":"Power","cost":"","description":"skulmod:Passive: Gain Vigor on Evoke.\nskulmod:Bonepile: Channel a skulmod:Cannonball.\nskulmod:Swap: Channel 4 Cannonballs.","mod":"skulmod"},{"id":"skulmod:EternalForm","name":"Eternal Form","color":"Quartz_purple","rarity":"Rare","type":"Power","cost":"2","description":"~~- Ethereal. -~~\nDrawing a card skulmod:Mills a card.","mod":"skulmod"},{"id":"skulmod:EyeOfTheStorm","name":"Eye of the Storm","color":"Quartz_purple","rarity":"Rare","type":"Skill","cost":"1","description":"Gain 6 (9) Block, applying Vigor.","mod":"skulmod"},{"id":"skulmod:Concentration","name":"Focused Strike","color":"Quartz_purple","rarity":"Rare","type":"Skill","cost":"2","description":"Discard an Attack.\nGain Vigor equal to its damage.\n~~- Exhaust. -~~ ","mod":"skulmod"},{"id":"skulmod:FrostSkull","name":"Frost Skull","color":"Quartz_purple","rarity":"Rare","type":"Power","cost":"","description":"*Passive: Give Block lost at the start of the turn to ALL enemies.\nBonepile: Gain 1 skulmod:Frozen.\nSwap: Channel 2 skulmod:Blizzards.","mod":"skulmod"},{"id":"skulmod:FrozenSoulForm","name":"Frozen Soul Form","color":"Quartz_purple","rarity":"Rare","type":"Power","cost":"2","description":"~~- Ethereal. -~~\nIf you end your turn with [E] , spend it to Channel 2 (3) skulmod:Blizzards for each [E] left.","mod":"skulmod"},{"id":"skulmod:GuardianForm","name":"Guardian Form","color":"Quartz_purple","rarity":"Rare","type":"Power","cost":"2","description":"~~- Ethereal. -~~\nFor every 50 Block you gain, convert 2 (3) Dexterity to 2 (3) Strength.","mod":"skulmod"},{"id":"skulmod:HalloHallo","name":"Hallo Hallo","color":"Quartz_purple","rarity":"Rare","type":"Skill","cost":"1","description":"Channel 6 (8) skulmod:Empty_Head.\nExhaust.","mod":"skulmod"},{"id":"skulmod:Impregnable","name":"Impregnable","color":"Quartz_purple","rarity":"Rare","type":"Skill","cost":"1","description":"Gain 5 (8) skulmod:Oblivion.\nskulmod:Bonepile 2.","mod":"skulmod"},{"id":"skulmod:JackInTheBox","name":"Jack-In-The-Box!","color":"Quartz_purple","rarity":"Rare","type":"Skill","cost":"1 (0)","description":"Your next card will be played as if it were X-Cost, based on its cost.\nExhaust.","mod":"skulmod"},{"id":"skulmod:EntertainerForm","name":"Joker Form","color":"Quartz_purple","rarity":"Rare","type":"Power","cost":"2","description":"~~- Ethereal. -~~\nThe first time each turn you play an skulmod:Imitation, skulmod:Bonepile.","mod":"skulmod"},{"id":"skulmod:BlackbeardForm","name":"Nobeard Form","color":"Quartz_purple","rarity":"Rare","type":"Power","cost":"2","description":"~~- Ethereal. -~~\nRetain Attacks, and Channel 1 (2) skulmod:Cannonball (Cannonballs) for each.","mod":"skulmod"},{"id":"skulmod:OutlawForm","name":"Outlaw Form","color":"Quartz_purple","rarity":"Rare","type":"Power","cost":"2","description":"~~- Ethereal. -~~\nAt the end of each turn, gain 4 (5) Gold.","mod":"skulmod"},{"id":"skulmod:RageMode","name":"Rage Form","color":"Quartz_purple","rarity":"Rare","type":"Power","cost":"2","description":"~~- Ethereal. -~~\nWrath is 2 times as effective.\nPrevent Fatal damage in Wrath once.","mod":"skulmod"},{"id":"skulmod:RigTheGame","name":"Rig The Game","color":"Quartz_purple","rarity":"Rare","type":"Skill","cost":"1","description":"Add 1 card from your draw pile to your hand.\nPut 1 card from your hand on top of your draw pile.\n~~- Exhaust. -~~ ","mod":"skulmod"},{"id":"skulmod:RipPockets","name":"Rip Pockets","color":"Quartz_purple","rarity":"Rare","type":"Skill","cost":"2","description":"Apply 10 (18) skulmod:Ripped_Pocket.\nGain 10 (18) Gold.","mod":"skulmod"},{"id":"skulmod:RoyalFlush","name":"Royal Flush","color":"Quartz_purple","rarity":"Rare","type":"Skill","cost":"2 (1)","description":"skulmod:Gamble 7 times.","mod":"skulmod"},{"id":"skulmod:SageForm","name":"Sage Form","color":"Quartz_purple","rarity":"Rare","type":"Power","cost":"2","description":"~~- Ethereal. -~~\nApplying a power to an enemy deals 3 damage.","mod":"skulmod"},{"id":"skulmod:WitchsGuidance","name":"Skull, Bone, Spirit","color":"Quartz_purple","rarity":"Rare","type":"Skill","cost":"1","description":"skulmod:Bonepile 4.\nChannel 4 skulmod:Empty_Head.\n~~- Exhaust. -~~ ","mod":"skulmod"},{"id":"skulmod:SniperForm","name":"Sniper Form","color":"Quartz_purple","rarity":"Rare","type":"Power","cost":"2","description":"Ethereal.\n (*)Attacks apply Lock-On.\nSkills grant Temporary Focus.\nAttack damage is 3.","mod":"skulmod"},{"id":"skulmod:Speedrun","name":"Speedrun","color":"Quartz_purple","rarity":"Rare","type":"Skill","cost":"1 (0)","description":"*Reshuffle your discard pile into your draw pile.","mod":"skulmod"},{"id":"skulmod:TechnicalJab","name":"Technical Jab","color":"Quartz_purple","rarity":"Rare","type":"Attack","cost":"2","description":"Deal 0 damage, equal to your missing health.\n~~- Exhaust. -~~ ","mod":"skulmod"},{"id":"skulmod:AbsoluteSkull","name":"The Absolute","color":"Quartz_purple","rarity":"Rare","type":"Power","cost":"","description":"*Passive: Playing a skulmod:Grapple grants skulmod:Herculean_Strength.\nBonepile: Complete 3 skulmod:Labors.\nSwap: Complete 12 Labors and play a random Grapple.","mod":"skulmod"},{"id":"skulmod:WarlordForm","name":"Warlord Form","color":"Quartz_purple","rarity":"Rare","type":"Power","cost":"2","description":"~~- Ethereal. -~~\nThe first Strike you play each turn has its cost reduced by 1 this combat.","mod":"skulmod"}],"relics":[{"id":"skulmod:Reassemble","name":"Reassembly","tier":"Starter","pool":"Quartz_purple","description":"Start with a random Skull. The first time you take Fatal damage, heal to 30 HP.","flavorText":"Bundle with Lizard Tail for maximum Reassemblage!","mod":"skulmod"},{"id":"skulmod:Centauros","name":"Centauros","tier":"Uncommon","pool":"Quartz_purple","description":"skulmod:Quintessence.\nOnce per combat, right click to deal 9 damage to a random enemy and inflict skulmod:Wedged_Spear.","flavorText":"\"A race of half-human, half horse beings with high intelligence and excellent hunting skills.\"","mod":"skulmod"},{"id":"skulmod:LuckAddiction","name":"Luck Addiction","tier":"Uncommon","pool":"Quartz_purple","description":"When you lose a skulmod:Gamble, randomly deal damage equal to half your Strength, Dexterity, and Focus.","flavorText":"Sometimes it's the thrill that's more appealing than the reward. ...Not often.","mod":"skulmod"},{"id":"skulmod:ChampionshipMatch","name":"Prize Match","tier":"Uncommon","pool":"Quartz_purple","description":"When you end your turn in Wrath, gain 1 Strength. When you exit Wrath, lose ALL Strength gained from this relic.","flavorText":"Undefeated, living or dead. Not as far as you know, at least.","mod":"skulmod"},{"id":"skulmod:EternalHunt","name":"Zoomies","tier":"Uncommon","pool":"Quartz_purple","description":"At the start of combat and each time you Reshuffle, shuffle an Acceleration into your draw pile.","flavorText":"The hunt never ends, not unless the Witch says \"Dinner Time\". You don't have to be alive to enjoy good food.","mod":"skulmod"},{"id":"skulmod:SlimeKing","name":"Slime King","tier":"Rare","pool":"Quartz_purple","description":"At the start of combat, add a copy of a random card you own to your hand. It varies between 25% and 200% effectiveness.","flavorText":"Oooh, a free body!","mod":"skulmod"},{"id":"skulmod:SpeedAltar","name":"*Altar of Speed","tier":"Special","pool":"Quartz_purple","description":"A memory of what almost was. Right Click this at a Rest Site to spend 10 Bone Fragments to start combat with 1 Plated Armor, up to 8 stacks.","flavorText":"It was so useful you decided to take it with you.","mod":"skulmod"},{"id":"skulmod:DamageAltar","name":"*Altar of Strength","tier":"Special","pool":"Quartz_purple","description":"A memory of what almost was. Right Click this at a Rest Site to spend 10 Bone Fragments to gain 1 Vigor each turn, up to 8 stacks.","flavorText":"It was so useful you decided to take it with you.","mod":"skulmod"},{"id":"skulmod:HealthAltar","name":"*Altar of Vitality","tier":"Special","pool":"Quartz_purple","description":"A memory of what almost was. Right Click this at a Rest Site to spend 20 Bone Fragments to gain 4 Max HP, up to 28 HP.","flavorText":"It was so useful you decided to take it with you.","mod":"skulmod"},{"id":"skulmod:BoneFragments","name":"*Bone Fragments","tier":"Special","pool":"Quartz_purple","description":"A memory of what almost was. A pouch that holds Bone Fragments obtained by shattering skulmod:Skulls. You can use them with Altar relics to gain permanent scaling stats.","flavorText":"You're a skeleton so you have a use for these, right?","mod":"skulmod"},{"id":"skulmod:SwapSkull","name":"*Swap Button","tier":"Special","pool":"Quartz_purple","description":"Right Click to skulmod:Swap to your inactive skulmod:Skull. Has no cooldown.","flavorText":"It's a little worn out, but that adds character. An item used for testing that some might find useful to explore the mod.","mod":"skulmod"},{"id":"skulmod:BestFriend","name":"Bestest Friend","tier":"Special","pool":"Quartz_purple","description":"Occasionally finds flowers that heal 1-4 HP after combat.\nYou don't think you could un-live with yourself if anything happened to her.","flavorText":"She's good enough at hide and seek that you don't feel at all worried about the monsters finding her.","mod":"skulmod"},{"id":"skulmod:HuntersGift","name":"Hunter's Gift","tier":"Boss","pool":"Quartz_purple","description":"On pickup, choose a skulmod:Skull to add to your deck.","flavorText":"Another one? You're greedy like an ogre.","mod":"skulmod"},{"id":"skulmod:IcedTea","name":"Original Iced Tea (a lot of ice)","tier":"Boss","pool":"Quartz_purple","description":"Prevent the next 44 HP you would have lost.","flavorText":"The Death Knight's favorite drink, there's so much ice you can hide behind it.","mod":"skulmod"},{"id":"skulmod:PerfectBlow","name":"Bottled Violence","tier":"Shop","pool":"","description":"Upon pickup, choose any card in your deck. It's treated as a Strike.","flavorText":"For your safety, please do not unbottle him. He's been charging up a long time in there.","mod":"skulmod"},{"id":"skulmod:DarkMirror","name":"Dark Mirror","tier":"Shop","pool":"Quartz_purple","description":"Upon pickup, obtain an additional copy of a card in your deck.\nIf that card is a Skull, create a random rare Skull instead.","flavorText":"The world looks funny in this.","mod":"skulmod"}],"potions":[{"id":"skulmod:Calcium","name":"Calcium","rarity":"Uncommon","description":"Bonepile 4.","mod":"skulmod"},{"id":"skulmod:SwapPotion","name":"Unstable Quartz","rarity":"Rare","description":"Pay 1 [E] to Swap.\nUnaffected by Potency.","mod":"skulmod"}],"creatures":[{"id":"LittleBone","name":"The Hero Slayer","type":"Player","minHP":"53","maxHP":"59","minHPA":"47","maxHPA":"52","mod":"skulmod"}],"keywords":[{"name":"Absolute Zero","description":"3: Once every two turns, Evoking channels a Frost orb.\n5: At the start of your turn, Evoke an orb.\nMasterpiece 6: Gain 1 Focus.","mod":"skulmod"},{"name":"Arrow","description":"Evoke: Deal 3 damage. Evoke ALL other arrows.\nPassive: Channel 1 Arrow at the start of your turn.","mod":"skulmod"},{"name":"Artifact","description":" 2: Channel a Meteor at the start of combat.\n5: Channel a Meteor every 3 turns.\nMasterpiece 6: Gain 1 Focus.","mod":"skulmod"},{"name":"Barrier","description":"Passive: At the end of your turn, gain 1 Dexterity until your next turn.\nEvoke: Gain 1 Dexterity until your next turn.","mod":"skulmod"},{"name":"Bleached","description":"Card cannot be Duplicated, Double Tapped, Burst, or Amplified.","mod":"skulmod"},{"name":"Blizzard","description":"Passive: At the end of your turn, ALL enemies lose HP equal to their Block, up to 2.\nEvoke: EVERYONE gains 2 Block.","mod":"skulmod"},{"name":"Bone","description":"3: Your first Swap each combat will grant Buffer.","mod":"skulmod"},{"name":"Bone Scream","description":"At the end of the turn, remove all powers and die. When dealing Fatal Attack damage, remove this. During Boss or Elite combat, die next turn instead.","mod":"skulmod"},{"name":"Bonepile","description":"A triggered effect based on your active Skull.\nDefaults to 2 Block.","mod":"skulmod"},{"name":"Burn","description":"Unblocked Non-Attack damage against the owner will be doubled once.","mod":"skulmod"},{"name":"Cannonball","description":"Evoke: Add a Fire! to your hand, or increase the damage if you already have one. Every fourth Cannonball is enhanced.","mod":"skulmod"},{"name":"Charge","description":"After gathering 5 stacks, choose an Attack. It becomes a 3 cost Strike with increased effects.","mod":"skulmod"},{"name":"Charged","description":"Warrior can Charge cards.\nA Charged card's cost becomes 3, and its effects increase based on the cost increase.\nCharged cards are treated as Strikes.","mod":"skulmod"},{"name":"Concentration","description":"Deals damage when reduced. When removed, deal the total damage dealt to ALL enemies.","mod":"skulmod"},{"name":"Counterattack","description":"Deal non-attack damage equal to the unblocked damage taken.","mod":"skulmod"},{"name":"Courage","description":"3: Gain 1 Strength.\n5: Gain 2 Strength.\n\nMasterpiece\n8: Gain 4 Strength.","mod":"skulmod"},{"name":"Embrace","description":"Temporarily lose HP until the start of your next turn. You can die from the HP loss.","mod":"skulmod"},{"name":"Empty Head","description":"Evoke: Bonepile","mod":"skulmod"},{"name":"Excessive Bleeding","description":"3: Your first attack each turn Wounds the target for half its damage.\n4: Your first attack each turn Wounds the target for full damage.\nMasterpiece 6: Your Wounding attacks deal 20% more damage.\n","mod":"skulmod"},{"name":"Fortress","description":"2: Gain 2 Block each turn, affected by Dexterity.\n5: Gain 2 more Block each turn.\nMasterpiece 6: Gain 2 Dexterity.","mod":"skulmod"},{"name":"Frozen","description":"You take and deal 1 less damage this turn.","mod":"skulmod"},{"name":"Gamble","description":"20% chance to gain 1 Strength, Dexterity, or Focus.","mod":"skulmod"},{"name":"Grapple","description":"A 2 damage Attack that costs 0 and Retains. At 3 or more stacks of Herculean Strength, they become Enhanced.","mod":"skulmod"},{"name":"Harvest","description":"Apply the following to EVERYONE:\n20 Souls: 2 Strength.\n40 Souls: 2 Vulnerable.\n60+ Souls: YOU become immune to death this turn.","mod":"skulmod"},{"name":"Herculean Strength","description":"Until the end of the turn, exponentially increases the damage of all Grapples by 50% per stack.","mod":"skulmod"},{"name":"Imitation","description":"A random card of any color. Its cost becomes 0 and it Purges. Imitations in your hand are Purged when you play a card.","mod":"skulmod"},{"name":"Item","description":"Increase the listed Set Effect permanently on pickup. Purges at the start of combat if it has no other effects.","mod":"skulmod"},{"name":"Labor","description":"After completing 12 Labors, add a random Grapple to your hand.","mod":"skulmod"},{"name":"Masterpiece","description":"3: Gain 1 Strength, Dexterity, and Focus.\n5: Unlock the Masterpiece effect of all your current sets.","mod":"skulmod"},{"name":"Meteor","description":"Evoke: Randomly deal b1 damage 1 time.","mod":"skulmod"},{"name":"Mill","description":"Discard a card from the top of your draw pile.","mod":"skulmod"},{"name":"Multiword Keyword","description":"Make sure the first element in the NAMES is the same as your PROPER_NAME. The rest should use _ to replace spaces and be entirely lowercase. In card text, you'll use the underscore versions.","mod":"skulmod"},{"name":"Oblivion","description":"Reduce the next unblocked damage you take once.\nOnce per turn, increase the next damage you deal.","mod":"skulmod"},{"name":"Omen","description":"1: Take 50% more damage.\n2: Take 100% more damage.\n3: Take 150% more damage.","mod":"skulmod"},{"name":"Passive","description":"A constant effect provided by the active Skull.","mod":"skulmod"},{"name":"Pay","description":"Use Gold to play this card. Cannot be played without Gold.","mod":"skulmod"},{"name":"Peerless","description":"Cost has been increased, and the attack has become single target. Refund twice the card's cost when played.","mod":"skulmod"},{"name":"Quintessence","description":"You can use this relic at ANY time, including the enemy's turn.","mod":"skulmod"},{"name":"Revenge","description":"3: Inflict 25% of the first damage you take each turn to the attacker as Revenge.\n5: The Revenge applied becomes 50%.\nMasterpiece 6: Also gain [E] the turn after you take unblocked damage.\n","mod":"skulmod"},{"name":"Ripped Pocket","description":"Attacking the target removes half of this, at least 5, and grants Gold equal to that amount.","mod":"skulmod"},{"name":"Skull","description":"Your active Skull changes your Passive and Bonepile. If you own more than 2 Skulls at the start of combat, shatter your choice until you have 2.\n\nSkulls are always Exhausted, cannot upgrade, and cannot be bottled.","mod":"skulmod"},{"name":"Soul","description":"A permanent power. As Grim Reaper, Attacks kill units under a percentage of YOUR missing HP, based on your Souls.","mod":"skulmod"},{"name":"Stamina","description":"Reduce this to heal after taking damage.","mod":"skulmod"},{"name":"Swap","description":"Your inactive Skull becomes active and triggers its Swap effect.","mod":"skulmod"},{"name":"Tactics","description":"After contemplating 8 strategies, create a Strategy Book in your hand.","mod":"skulmod"},{"name":"Total Cards","description":"The sum of your discard pile, draw pile, and hand.","mod":"skulmod"},{"name":"Unshackled","description":"The next time you start or end your turn, gain 1 Strength.","mod":"skulmod"},{"name":"Wedged Spear","description":"After 3 turns or when the target dies, refresh the cooldown of Centauros.","mod":"skulmod"},{"name":"This is displayed in the tooltip.","description":"This is displayed in the tooltip. Note, spaces are not allowed in NAMES. Also, they should be entirely lowercase. For multi-word keywords, see the next one.","mod":"skulmod"},{"name":"Grit","description":"Retain the next 1 Block you'd lose at the start of the turn.","mod":"skulmod"},{"name":"Unobstructed","description":"Damage not prevented by emporary HP or Block.","mod":"skulmod"}],"mods":[{"name":"skulmod","version":"2.0.7","authors":["Svitasch"],"credits":"","description":"Reassemble, rise, and re-rise again! \n Skul, Hero Slayer, Little Bone, no matter what you call him it won’t change that he’s here for another adventure! The last skeleton and the hero of Demonkind in their hour of need, Little Bone ascends the spire in search of the new source of Dark Quartz spreading across Harmonia. Will he make it to the top to put an end to this once and for all, or will he end up disassembled at the foot of the spire?","mts_version":"3.30.0","sts_version":"12-18-2022","dependencies":["basemod","stslib"],"optional_dependencies":[]}]}